simple_ttl_cache.py
simple_ttl_cache-0.0.1.dist-info/LICENSE
simple_ttl_cache-0.0.1.dist-info/METADATA
simple_ttl_cache-0.0.1.dist-info/WHEEL
simple_ttl_cache-0.0.1.dist-info/top_level.txt
simple_ttl_cache-0.0.1.dist-info/RECORD
